copydetect/__init__.py
copydetect/__main__.py
copydetect/detector.py
copydetect/pywinnow.py
copydetect/utils.py
plagiarismchecker-0.1.0.dist-info/LICENSE
plagiarismchecker-0.1.0.dist-info/METADATA
plagiarismchecker-0.1.0.dist-info/WHEEL
plagiarismchecker-0.1.0.dist-info/entry_points.txt
plagiarismchecker-0.1.0.dist-info/top_level.txt
plagiarismchecker-0.1.0.dist-info/RECORD
